vmbpy/__init__.py
vmbpy/camera.py
vmbpy/error.py
vmbpy/feature.py
vmbpy/featurecontainer.py
vmbpy/frame.py
vmbpy/interface.py
vmbpy/localdevice.py
vmbpy/shared.py
vmbpy/stream.py
vmbpy/transportlayer.py
vmbpy/vmbsystem.py
vmbpy/c_binding/__init__.py
vmbpy/c_binding/vmb_c.py
vmbpy/c_binding/vmb_common.py
vmbpy/c_binding/vmb_image_transform.py
vmbpy/c_binding/wrapped_types.py
vmbpy/c_binding/lib/VmbC.xml
vmbpy/c_binding/lib/libVmbC.so
vmbpy/c_binding/lib/libVmbImageTransform.so
vmbpy/c_binding/lib/GenICam/libGCBase_GNU8_4_0_v3_2_AVT.so
vmbpy/c_binding/lib/GenICam/libGenApi_GNU8_4_0_v3_2_AVT.so
vmbpy/c_binding/lib/GenICam/libLog_GNU8_4_0_v3_2_AVT.so
vmbpy/c_binding/lib/GenICam/libMathParser_GNU8_4_0_v3_2_AVT.so
vmbpy/c_binding/lib/GenICam/libNodeMapData_GNU8_4_0_v3_2_AVT.so
vmbpy/c_binding/lib/GenICam/libXmlParser_GNU8_4_0_v3_2_AVT.so
vmbpy/c_binding/lib/GenICam/liblog4cpp_GNU8_4_0_v3_2_AVT.so
vmbpy/util/__init__.py
vmbpy/util/context_decorator.py
vmbpy/util/log.py
vmbpy/util/runtime_type_check.py
vmbpy/util/scoped_log.py
vmbpy/util/tracer.py
vmbpy/util/vmb_enum.py
vmbpy-1.1.1.dist-info/LICENSE.txt
vmbpy-1.1.1.dist-info/METADATA
vmbpy-1.1.1.dist-info/WHEEL
vmbpy-1.1.1.dist-info/top_level.txt
vmbpy-1.1.1.dist-info/RECORD
