Metadata-Version: 2.1
Name: vmbpy
Version: 1.1.1
Summary: Python bindings for VmbC
Home-page: https://github.com/alliedvision/vmbpy
Author: Allied Vision Technologies
License: BSD 2-Clause License
Project-URL: Bug Tracker, https://github.com/alliedvision/vmbpy/issues
Classifier: Programming Language :: Python :: 3
Classifier: Operating System :: OS Independent
Requires-Python: >=3.7
License-File: LICENSE.txt
Provides-Extra: numpy
Requires-Dist: numpy ; extra == 'numpy'
Provides-Extra: opencv
Requires-Dist: opencv-python ; extra == 'opencv'
Provides-Extra: test
Requires-Dist: unittest-xml-reporting ; extra == 'test'
Requires-Dist: flake8 ; extra == 'test'
Requires-Dist: flake8-junit-report ; extra == 'test'
Requires-Dist: mypy ; extra == 'test'
Requires-Dist: coverage ; extra == 'test'
